[
    {
        "ciudad": "Madrid",
        "nombre": "Parque Warner",
        "imagen": "warner.jpg",
        "descripcion": "Parque temático con atracciones para todas las edades.",
        "edad": "Todas las edades",
        "precio": "Desde 30€",
        "ubicacion": "San Martín de la Vega",
        "enlace": "https://www.parquewarner.com/"
    },
    {
        "ciudad": "Barcelona",
        "nombre": "Zoo de Barcelona",
        "imagen": "zoo.jpg",
        "descripcion": "Descubre animales de todo el mundo en un entorno natural.",
        "edad": "Todas las edades",
        "precio": "Desde 21€",
        "ubicacion": "Parc de la Ciutadella",
        "enlace": "https://www.zoobarcelona.cat/"
    }
]
